{
    "Anti-aphrodisiac": "A substance capable of blunting the venereal appetite",
    "Anti-bilious": "Opposed to biliousness, acting on the bile",
    "Anti-emetic": "A remedy for vomiting",
    "Anti-epileptic": "Opposed to epilepsy, relieving fits",
    "Anti-hysteric": "A remedy for hysteria",
    "Anthilitic": "Preventing the formation of calculi in the urinary organs",
    "Anti-periodic": "Arresting morbid periodical movements",
    "Anti-phlogistic": "Opposed to inflammation",
    "Anti-rheumatic": "Relieving or curing rheumatism",
    "Anti-scorbutic": "Curing or preventing scurvy",
    "Anti-septic": "Opposed to putrefaction",
    "Anti-spasmotic": "Relieving or preventing spasm",
    "Anti-syphilitic": "Opposed to or curing venereal diseases",
    "Anti-venomous": "Used against bites of insects, snakes, etc.",
    "Counter-irritant": "Causing irritation in one part to relieve pain in another part",
    "Depilatory": "Removing superfluous hair",
    "Detersive": "Detergent",
    "Escharotic": "A substance which, applied to a living part, causes an eschar",
    "Female complaints": "Ailments peculiar to women, as dismenorrhœa, amenorrhœa, etc.",
    "Abortive": "A medicine which claims the property of causing abortion",
    "Acidulous": "Substances which possess a sourish taste",
    "Acrid": "Hot, biting, irritating",
    "Adenagic": "Relieving or arresting glandular pain",
    "Alexipharmic": "Preventing the bad effects of poisons inwardly",
    "Alterative": "Producing a salutary change without perceptible evacuation",
    "Anodyne": "Relieving pain, or causing it to cease",
    "Anthelmintic": "A remedy which expels worms",
    "Aperient": "Gently laxative, without purging",
    "Aphrodisiac": "Medicine believed capable of exciting the venereal appetite",
    "Aromatic": "Odoriferous, stimulant, spicy",
    "Astringent": "Having the property of constringing the organic texture",
    "Balsamic": "Healing or soothing to inflamed parts",
    "Bitter": "Having a tonic effect",
    "Carminative": "Expelling wind from the bowels",
    "Cathartic": "Increasing evacuations from the bowels",
    "Caustic": "The property of burning or disorganizing animal substance",
    "Cephalic": "Relating to diseases of the head",
    "Cholagogue": "Increasing the flow of bile",
    "Condiment": "Improving the saver of food, as salt, pepper, salad, etc.",
    "Cordial": "A worm stomachic, exciting the heart",
    "Cosmetic": "Used for improving the complexion",
    "Demulcent": "Soothing, mucilaginous, relieving inflammation",
    "Deobstruent": "Removing obstructions, aperient in a general sense",
    "Depurative": "Purifying the blood",
    "Dessicative": "Drying the moisture of wounds and ulcers",
    "Detergent": "Cleansing to wounds, boils, or ulcers",
    "Diaphoretic": "Producing insensible perspiration",
    "Discutient": "Dispelling or resolving tumors",
    "Diuretic": "Increasing the secretion and flow of urine",
    "Drastic": "Powerfully cathartic",
    "Edible": "Fit to be eaten",
    "Emetic": "Producing or causing vomiting",
    "Emmenagogue": "Promoting menstruation",
    "Emollient": "Softening to inflamed parts, soothing",
    "Esculent": "Eatable as food",
    "Exanthematous": "Relating to eruption or skin diseases",
    "Excitant": "Producing excitement, stimulant",
    "Expectorant": "A medicine capable of facilitating expectoration",
    "Farinaceous": "Containing farina, mealy, employed as nutriment",
    "Febrifuge": "Abating or driving away fever",
    "Fœtid": "Bad smelling, nauseous, stinking",
    "Forage": "Used as food for domestic animals",
    "Fumigating": "Disinfecting by burning substances which counteract obnoxious odors",
    "Galactagogue": "Favoring the secretion of milk",
    "Hepatic": "Relating to diseases of the liver",
    "Herpatic": "Relating to or curing eruptions or skin diseases, as ringworm",
    "Hydragogue": "Medicines that cause watery evacuations and believed capable of expelling serum",
    "Hypnotic": "Producing or inducing sleep",
    "Insecticide": "A substance that destroys insects",
    "Irritant": "Causing irritation",
    "Laxative": "A medicine that acts gently on the bowels, without griping",
    "Lenitive": "Allaying irritation, also laxative",
    "Lithontryptic": "Medicine believed to dissolve calculi in the urinary organs",
    "Maturating": "Favoring the maturation or ripening of tumors, boils, and ulcers",
    "Mucilaginous": "Gummy, glutinous, viscid, demuculent",
    "Narcotic": "Stupefying, sedative, poisonous",
    "Nauseant": "Causing inclination to vomit",
    "Nephreticum": "Relating to or curing kidney complaints",
    "Nervine": "Allaying nervous excitement, acting on the nervous system",
    "Nutritious": "Having the quality of nourishing or sustaining life",
    "Opthalmicum": "A remedy for diseases of the eye",
    "Ornamental": "Cultivated for ornament",
    "Parturient": "A medicine that induces or promotes labor or child-birth",
    "Pectoral": "Medicines considered proper for relieving afflictions of the chest",
    "Perfume": "Used for its fragrance",
    "Poison": "Producing death if taken in improper doses",
    "Pungent": "Biting, hot, acrid, prickly to the taste",
    "Purgative": "A medicine that physics more powerfully than a cathartic",
    "Refrigerant": "Depressing the morbid temperature of the body, cooling",
    "Resolvent": "Discutient, dispelling or resolving tumors",
    "Rubefacient": "Producing redness of the skin",
    "Saccharine": "Containing sugar, sweetish",
    "Salad": "Fresh herbs eaten as condiments or as food",
    "Saline": "Containing the properties of salt",
    "Saponaceous": "Soapy, making a lather with water",
    "Sedative": "Directly depressing to the vital forces",
    "Sialogogue": "Provoking the secretion of saliva",
    "Sternutatory": "A substance which provokes sneezing",
    "Stimulant": "Exciting or inducing organic action of the animal economy",
    "Stomachic": "Strengthening and giving tone to the stomach, tonic",
    "Styptic": "Externally astringent, arresting hemorrhage or bleeding",
    "Sudorific": "A medicine which provokes sweating",
    "Tonic": "Permanently strengthening, in a durable manner invigorating",
    "Vermifuge": "Anthelmintic, expelling worms",
    "Vesicant": "Producing blisters",
    "Viscid": "Having a glutinous or ropy consistency, tenacious",
    "Vulnerary": "Healing to fresh cuts or wounds"
}